<?xml version="1.0" encoding="utf-8"?>
<!DOCTYPE hibernate-mapping PUBLIC "-//Hibernate/Hibernate Mapping DTD 3.0//EN"
"http://hibernate.sourceforge.net/hibernate-mapping-3.0.dtd">
<!-- 
    Mapping file autogenerated by MyEclipse Persistence Tools
-->
<hibernate-mapping>
    <class name="com.dao.SurveyCheck" table="survey_check" catalog="health">
        <id name="uid" type="java.lang.Integer">
            <column name="uid" />
            <generator class="assigned" />
        </id>
        <property name="high" type="java.lang.String">
            <column name="high" />
        </property>
        <property name="weight" type="java.lang.String">
            <column name="weight" />
        </property>
        <property name="xiongwei" type="java.lang.String">
            <column name="xiongwei" />
        </property>
        <property name="gaoya" type="java.lang.String">
            <column name="gaoya" />
        </property>
        <property name="diya" type="java.lang.String">
            <column name="diya" />
        </property>
        <property name="zaobo" type="java.lang.String">
            <column name="zaobo" />
        </property>
        <property name="stt" type="java.lang.String">
            <column name="stt" />
        </property>
        <property name="fangchan" type="java.lang.String">
            <column name="fangchan" />
        </property>
        <property name="zuoxinshi" type="java.lang.String">
            <column name="zuoxinshi" />
        </property>
        <property name="xb01" type="java.lang.String">
            <column name="xb01" />
        </property>
        <property name="xb02" type="java.lang.String">
            <column name="xb02" />
        </property>
        <property name="xb03" type="java.lang.String">
            <column name="xb03" />
        </property>
        <property name="xb04" type="java.lang.String">
            <column name="xb04" />
        </property>
        <property name="xb05" type="java.lang.String">
            <column name="xb05" />
        </property>
        <property name="xb06" type="java.lang.String">
            <column name="xb06" />
        </property>
        <property name="xb07" type="java.lang.String">
            <column name="xb07" />
        </property>
        <property name="xb08" type="java.lang.String">
            <column name="xb08" />
        </property>
        <property name="sys01" type="java.lang.String">
            <column name="sys01" />
        </property>
        <property name="sys02" type="java.lang.String">
            <column name="sys02" />
        </property>
        <property name="sys03" type="java.lang.String">
            <column name="sys03" />
        </property>
        <property name="sys04" type="java.lang.String">
            <column name="sys04" />
        </property>
        <property name="sys05" type="java.lang.String">
            <column name="sys05" />
        </property>
        <property name="sys06" type="java.lang.String">
            <column name="sys06" />
        </property>
        <property name="sys07" type="java.lang.String">
            <column name="sys07" />
        </property>
        <property name="sys08" type="java.lang.String">
            <column name="sys08" />
        </property>
        <property name="sys09" type="java.lang.String">
            <column name="sys09" />
        </property>
        <property name="sys10" type="java.lang.String">
            <column name="sys10" />
        </property>
        <property name="sys11" type="java.lang.String">
            <column name="sys11" />
        </property>
        <property name="sys12" type="java.lang.String">
            <column name="sys12" />
        </property>
        <property name="sys13" type="java.lang.String">
            <column name="sys13" />
        </property>
        <property name="sys14" type="java.lang.String">
            <column name="sys14" />
        </property>
        <property name="sys15" type="java.lang.String">
            <column name="sys15" />
        </property>
        <property name="sys16" type="java.lang.String">
            <column name="sys16" />
        </property>
        <property name="sys17" type="java.lang.String">
            <column name="sys17" />
        </property>
        <property name="sys18" type="java.lang.String">
            <column name="sys18" />
        </property>
        <property name="sys19" type="java.lang.String">
            <column name="sys19" />
        </property>
    </class>
</hibernate-mapping>
